appserver_secrets/__init__.py
appserver_secrets/__main__.py
appserver_secrets/secrets.py
appserver_sdk_python_secrets-0.1.0.dist-info/entry_points.txt
appserver_sdk_python_secrets-0.1.0.dist-info/LICENSE
appserver_sdk_python_secrets-0.1.0.dist-info/METADATA
appserver_sdk_python_secrets-0.1.0.dist-info/WHEEL
appserver_sdk_python_secrets-0.1.0.dist-info/RECORD
