Metadata-Version: 2.3
Name: appserver-sdk-python-secrets
Version: 0.1.0
Summary: Gerenciador de segredos local usando keyring, com índice em JSON.
License: MIT
Keywords: secrets,keyring,appserver,segurança,armazenamento seguro
Author: Iran Ribeiro
Author-email: iranribeiro22@email.com
Requires-Python: >=3.8
Classifier: License :: OSI Approved :: MIT License
Classifier: Programming Language :: Python :: 3
Classifier: Programming Language :: Python :: 3.8
Classifier: Programming Language :: Python :: 3.9
Classifier: Programming Language :: Python :: 3.10
Classifier: Programming Language :: Python :: 3.11
Classifier: Programming Language :: Python :: 3.12
Classifier: Programming Language :: Python :: 3.13
Requires-Dist: keyring (>=25.0.0)
Project-URL: Repository, https://github.com/appserver-sdk/python-secrets
